vizdnn/__init__.py
vizdnn-0.0.4.dist-info/LICENSE
vizdnn-0.0.4.dist-info/METADATA
vizdnn-0.0.4.dist-info/WHEEL
vizdnn-0.0.4.dist-info/top_level.txt
vizdnn-0.0.4.dist-info/RECORD
