Metadata-Version: 2.1
Name: vizdnn
Version: 0.0.4
Summary: Deep Neural Network Vizualizer
Home-page: https://github.com/karthikziffer/vizdnn
Author: Karthik
Author-email: karthik.cool1300@gmail.com
License: MIT
Platform: UNKNOWN
Requires-Dist: keras
Requires-Dist: matplotlib
Requires-Dist: numpy
